{"note":"This file is an internal implementation detail to speed up HTML report generation. Its format can change at any time. You might be looking for the JSON report: https://coverage.rtfd.io/cmd.html#cmd-json","format":5,"version":"7.9.1","globals":"076f7d58943dee8b9ca4f498c255fe7e","files":{"z_509fd8af0f7a1b49_admin_py":{"hash":"cb38aa6087532211b3dbd5af6d681e75","index":{"url":"z_509fd8af0f7a1b49_admin_py.html","file":"accounts/admin.py","description":"","nums":{"precision":0,"n_files":1,"n_statements":41,"n_excluded":0,"n_missing":0,"n_branches":0,"n_partial_branches":0,"n_missing_branches":0}}},"z_509fd8af0f7a1b49_forms_py":{"hash":"d360cbb0c59506795cb39a3dd8d80deb","index":{"url":"z_509fd8af0f7a1b49_forms_py.html","file":"accounts/forms.py","description":"","nums":{"precision":0,"n_files":1,"n_statements":50,"n_excluded":0,"n_missing":0,"n_branches":0,"n_partial_branches":0,"n_missing_branches":0}}},"z_509fd8af0f7a1b49_models_py":{"hash":"5b237e668e4b4c611dfdf5522261bf62","index":{"url":"z_509fd8af0f7a1b49_models_py.html","file":"accounts/models.py","description":"","nums":{"precision":0,"n_files":1,"n_statements":25,"n_excluded":0,"n_missing":0,"n_branches":0,"n_partial_branches":0,"n_missing_branches":0}}},"z_509fd8af0f7a1b49_tests_py":{"hash":"cc2b7073a8e138a467d61469902a762e","index":{"url":"z_509fd8af0f7a1b49_tests_py.html","file":"accounts/tests.py","description":"","nums":{"precision":0,"n_files":1,"n_statements":103,"n_excluded":0,"n_missing":0,"n_branches":0,"n_partial_branches":0,"n_missing_branches":0}}},"z_509fd8af0f7a1b49_urls_py":{"hash":"3746fdda9b3905b57147f8a8ccd9a9aa","index":{"url":"z_509fd8af0f7a1b49_urls_py.html","file":"accounts/urls.py","description":"","nums":{"precision":0,"n_files":1,"n_statements":4,"n_excluded":0,"n_missing":0,"n_branches":0,"n_partial_branches":0,"n_missing_branches":0}}},"z_509fd8af0f7a1b49_views_py":{"hash":"fc21a944208a1ddf1956d84a752e1b3b","index":{"url":"z_509fd8af0f7a1b49_views_py.html","file":"accounts/views.py","description":"","nums":{"precision":0,"n_files":1,"n_statements":62,"n_excluded":0,"n_missing":1,"n_branches":0,"n_partial_branches":0,"n_missing_branches":0}}},"z_10fae538ba4e8521_api_py":{"hash":"65209a271092bab18107f669fbe0ada4","index":{"url":"z_10fae538ba4e8521_api_py.html","file":"api/api.py","description":"","nums":{"precision":0,"n_files":1,"n_statements":11,"n_excluded":0,"n_missing":0,"n_branches":0,"n_partial_branches":0,"n_missing_branches":0}}},"z_10fae538ba4e8521_filters_py":{"hash":"220f435ef3668b03ceb3b29aee9346cf","index":{"url":"z_10fae538ba4e8521_filters_py.html","file":"api/filters.py","description":"","nums":{"precision":0,"n_files":1,"n_statements":63,"n_excluded":0,"n_missing":5,"n_branches":0,"n_partial_branches":0,"n_missing_branches":0}}},"z_10fae538ba4e8521_serializers_py":{"hash":"45eea4fad28a8e1ea8180d67868c370f","index":{"url":"z_10fae538ba4e8521_serializers_py.html","file":"api/serializers.py","description":"","nums":{"precision":0,"n_files":1,"n_statements":111,"n_excluded":0,"n_missing":0,"n_branches":0,"n_partial_branches":0,"n_missing_branches":0}}},"z_10fae538ba4e8521_tests_py":{"hash":"05d741e2a73804e438f468e49440ae63","index":{"url":"z_10fae538ba4e8521_tests_py.html","file":"api/tests.py","description":"","nums":{"precision":0,"n_files":1,"n_statements":9,"n_excluded":0,"n_missing":0,"n_branches":0,"n_partial_branches":0,"n_missing_branches":0}}},"z_10fae538ba4e8521_views_py":{"hash":"c631c01fd1fd3556102593426ccd501f","index":{"url":"z_10fae538ba4e8521_views_py.html","file":"api/views.py","description":"","nums":{"precision":0,"n_files":1,"n_statements":93,"n_excluded":0,"n_missing":0,"n_branches":0,"n_partial_branches":0,"n_missing_branches":0}}},"z_2ecf1080f59d2c60_context_processors_py":{"hash":"508339e20e7179b2699cafb89f16cc02","index":{"url":"z_2ecf1080f59d2c60_context_processors_py.html","file":"buses/context_processors.py","description":"","nums":{"precision":0,"n_files":1,"n_statements":7,"n_excluded":0,"n_missing":0,"n_branches":0,"n_partial_branches":0,"n_missing_branches":0}}},"z_2ecf1080f59d2c60_jinja2_py":{"hash":"ac3a53399070b367c4a8c124eaee3933","index":{"url":"z_2ecf1080f59d2c60_jinja2_py.html","file":"buses/jinja2.py","description":"","nums":{"precision":0,"n_files":1,"n_statements":36,"n_excluded":0,"n_missing":2,"n_branches":0,"n_partial_branches":0,"n_missing_branches":0}}},"z_2ecf1080f59d2c60_settings_py":{"hash":"42cd9da0b1e4c47aae92aad83a1e8b30","index":{"url":"z_2ecf1080f59d2c60_settings_py.html","file":"buses/settings.py","description":"","nums":{"precision":0,"n_files":1,"n_statements":122,"n_excluded":5,"n_missing":30,"n_branches":0,"n_partial_branches":0,"n_missing_branches":0}}},"z_2ecf1080f59d2c60_tests_py":{"hash":"ba37c5ff4d695e20951eed6fca4760b9","index":{"url":"z_2ecf1080f59d2c60_tests_py.html","file":"buses/tests.py","description":"","nums":{"precision":0,"n_files":1,"n_statements":5,"n_excluded":0,"n_missing":0,"n_branches":0,"n_partial_branches":0,"n_missing_branches":0}}},"z_2ecf1080f59d2c60_urls_py":{"hash":"1a9041df09222605e67f16fe3dbcbcc8","index":{"url":"z_2ecf1080f59d2c60_urls_py.html","file":"buses/urls.py","description":"","nums":{"precision":0,"n_files":1,"n_statements":5,"n_excluded":0,"n_missing":0,"n_branches":0,"n_partial_branches":0,"n_missing_branches":0}}},"z_2ecf1080f59d2c60_utils_py":{"hash":"2e6d4f1c740bb4c023a9a24c5c4a8c43","index":{"url":"z_2ecf1080f59d2c60_utils_py.html","file":"buses/utils.py","description":"","nums":{"precision":0,"n_files":1,"n_statements":17,"n_excluded":0,"n_missing":0,"n_branches":0,"n_partial_branches":0,"n_missing_branches":0}}},"z_a23ebd71efc9294f_admin_py":{"hash":"96dd68df797d12186497c8f8d9964fc2","index":{"url":"z_a23ebd71efc9294f_admin_py.html","file":"busstops/admin.py","description":"","nums":{"precision":0,"n_files":1,"n_statements":318,"n_excluded":0,"n_missing":16,"n_branches":0,"n_partial_branches":0,"n_missing_branches":0}}},"z_a23ebd71efc9294f_forms_py":{"hash":"4af8d229f7a7dd47bc991d0d36693bce","index":{"url":"z_a23ebd71efc9294f_forms_py.html","file":"busstops/forms.py","description":"","nums":{"precision":0,"n_files":1,"n_statements":46,"n_excluded":0,"n_missing":0,"n_branches":0,"n_partial_branches":0,"n_missing_branches":0}}},"z_ce3c907b0b556e9c_import_noc_py":{"hash":"a4dd4a767b0d03f57ee0f08d8771f6f0","index":{"url":"z_ce3c907b0b556e9c_import_noc_py.html","file":"busstops/management/commands/import_noc.py","description":"","nums":{"precision":0,"n_files":1,"n_statements":128,"n_excluded":0,"n_missing":3,"n_branches":0,"n_partial_branches":0,"n_missing_branches":0}}},"z_ce3c907b0b556e9c_naptan_new_py":{"hash":"81e4167706f3c34f99ff26e98bf7dfe0","index":{"url":"z_ce3c907b0b556e9c_naptan_new_py.html","file":"busstops/management/commands/naptan_new.py","description":"","nums":{"precision":0,"n_files":1,"n_statements":143,"n_excluded":0,"n_missing":5,"n_branches":0,"n_partial_branches":0,"n_missing_branches":0}}},"z_ce3c907b0b556e9c_nptg_new_py":{"hash":"a93de7e83c0b7aef9afefe2385e4c2b1","index":{"url":"z_ce3c907b0b556e9c_nptg_new_py.html","file":"busstops/management/commands/nptg_new.py","description":"","nums":{"precision":0,"n_files":1,"n_statements":94,"n_excluded":0,"n_missing":7,"n_branches":0,"n_partial_branches":0,"n_missing_branches":0}}},"z_2000191b5cd11660_test_import_ie_py":{"hash":"08a43225b4637aea85f49bcfb07e13f9","index":{"url":"z_2000191b5cd11660_test_import_ie_py.html","file":"busstops/management/tests/test_import_ie.py","description":"","nums":{"precision":0,"n_files":1,"n_statements":63,"n_excluded":0,"n_missing":0,"n_branches":0,"n_partial_branches":0,"n_missing_branches":0}}},"z_2000191b5cd11660_test_import_naptan_py":{"hash":"c2225fc38df1d6bba9a84a13b2062456","index":{"url":"z_2000191b5cd11660_test_import_naptan_py.html","file":"busstops/management/tests/test_import_naptan.py","description":"","nums":{"precision":0,"n_files":1,"n_statements":67,"n_excluded":0,"n_missing":0,"n_branches":0,"n_partial_branches":0,"n_missing_branches":0}}},"z_2000191b5cd11660_test_import_nptg_py":{"hash":"7c353c060cfb9ac8d3140258a08695f8","index":{"url":"z_2000191b5cd11660_test_import_nptg_py.html","file":"busstops/management/tests/test_import_nptg.py","description":"","nums":{"precision":0,"n_files":1,"n_statements":31,"n_excluded":0,"n_missing":0,"n_branches":0,"n_partial_branches":0,"n_missing_branches":0}}},"z_2000191b5cd11660_test_import_operators_py":{"hash":"ff69571a17c47eaf2feda6c164c3088a","index":{"url":"z_2000191b5cd11660_test_import_operators_py.html","file":"busstops/management/tests/test_import_operators.py","description":"","nums":{"precision":0,"n_files":1,"n_statements":64,"n_excluded":0,"n_missing":0,"n_branches":0,"n_partial_branches":0,"n_missing_branches":0}}},"z_a23ebd71efc9294f_middleware_py":{"hash":"78663b7528e05f003e0216e04b3dafce","index":{"url":"z_a23ebd71efc9294f_middleware_py.html","file":"busstops/middleware.py","description":"","nums":{"precision":0,"n_files":1,"n_statements":28,"n_excluded":0,"n_missing":7,"n_branches":0,"n_partial_branches":0,"n_missing_branches":0}}},"z_a23ebd71efc9294f_models_py":{"hash":"41fa0904d1b5c6d1241064d657895c8c","index":{"url":"z_a23ebd71efc9294f_models_py.html","file":"busstops/models.py","description":"","nums":{"precision":0,"n_files":1,"n_statements":627,"n_excluded":0,"n_missing":25,"n_branches":0,"n_partial_branches":0,"n_missing_branches":0}}},"z_b8e363a838fda594_date_range_py":{"hash":"24f40479faa66df99ebe05446654d071","index":{"url":"z_b8e363a838fda594_date_range_py.html","file":"busstops/templatetags/date_range.py","description":"","nums":{"precision":0,"n_files":1,"n_statements":25,"n_excluded":0,"n_missing":3,"n_branches":0,"n_partial_branches":0,"n_missing_branches":0}}},"z_b8e363a838fda594_urlise_py":{"hash":"51c79292e49908d66d4302f0c175ddd1","index":{"url":"z_b8e363a838fda594_urlise_py.html","file":"busstops/templatetags/urlise.py","description":"","nums":{"precision":0,"n_files":1,"n_statements":16,"n_excluded":0,"n_missing":0,"n_branches":0,"n_partial_branches":0,"n_missing_branches":0}}},"z_a23ebd71efc9294f_test_admin_py":{"hash":"8b5b51f3e5ad80f2ea954909cc7ec661","index":{"url":"z_a23ebd71efc9294f_test_admin_py.html","file":"busstops/test_admin.py","description":"","nums":{"precision":0,"n_files":1,"n_statements":52,"n_excluded":0,"n_missing":0,"n_branches":0,"n_partial_branches":0,"n_missing_branches":0}}},"z_a23ebd71efc9294f_test_middleware_py":{"hash":"65b57bb31cfa2dcd394eb9fd917cf275","index":{"url":"z_a23ebd71efc9294f_test_middleware_py.html","file":"busstops/test_middleware.py","description":"","nums":{"precision":0,"n_files":1,"n_statements":10,"n_excluded":0,"n_missing":0,"n_branches":0,"n_partial_branches":0,"n_missing_branches":0}}},"z_a23ebd71efc9294f_test_models_py":{"hash":"19217757df1317dfa7cfd1a4952139c1","index":{"url":"z_a23ebd71efc9294f_test_models_py.html","file":"busstops/test_models.py","description":"","nums":{"precision":0,"n_files":1,"n_statements":143,"n_excluded":0,"n_missing":0,"n_branches":0,"n_partial_branches":0,"n_missing_branches":0}}},"z_a23ebd71efc9294f_test_views_py":{"hash":"02f33bee9d44f177e670b547dba43a95","index":{"url":"z_a23ebd71efc9294f_test_views_py.html","file":"busstops/test_views.py","description":"","nums":{"precision":0,"n_files":1,"n_statements":270,"n_excluded":0,"n_missing":0,"n_branches":0,"n_partial_branches":0,"n_missing_branches":0}}},"z_a23ebd71efc9294f_urls_py":{"hash":"571f365c3b60df95b96c974cfb9c4ad6","index":{"url":"z_a23ebd71efc9294f_urls_py.html","file":"busstops/urls.py","description":"","nums":{"precision":0,"n_files":1,"n_statements":20,"n_excluded":0,"n_missing":2,"n_branches":0,"n_partial_branches":0,"n_missing_branches":0}}},"z_a23ebd71efc9294f_utils_py":{"hash":"7288c8344d4e71038304d124c9b03b63","index":{"url":"z_a23ebd71efc9294f_utils_py.html","file":"busstops/utils.py","description":"","nums":{"precision":0,"n_files":1,"n_statements":11,"n_excluded":0,"n_missing":0,"n_branches":0,"n_partial_branches":0,"n_missing_branches":0}}},"z_a23ebd71efc9294f_views_py":{"hash":"f5dfe836556e71c0463e190aa96a9bf9","index":{"url":"z_a23ebd71efc9294f_views_py.html","file":"busstops/views.py","description":"","nums":{"precision":0,"n_files":1,"n_statements":628,"n_excluded":0,"n_missing":46,"n_branches":0,"n_partial_branches":0,"n_missing_branches":0}}},"z_3baf1eb7e8e062db_admin_py":{"hash":"e3455446a23371a810eb77512355d4ce","index":{"url":"z_3baf1eb7e8e062db_admin_py.html","file":"bustimes/admin.py","description":"","nums":{"precision":0,"n_files":1,"n_statements":113,"n_excluded":0,"n_missing":15,"n_branches":0,"n_partial_branches":0,"n_missing_branches":0}}},"z_3baf1eb7e8e062db_download_utils_py":{"hash":"36b83747f1c19e493989cd10399ea5c1","index":{"url":"z_3baf1eb7e8e062db_download_utils_py.html","file":"bustimes/download_utils.py","description":"","nums":{"precision":0,"n_files":1,"n_statements":32,"n_excluded":0,"n_missing":0,"n_branches":0,"n_partial_branches":0,"n_missing_branches":0}}},"z_3baf1eb7e8e062db_fields_py":{"hash":"611bd0cdabb8c822232dcefa5de114f7","index":{"url":"z_3baf1eb7e8e062db_fields_py.html","file":"bustimes/fields.py","description":"","nums":{"precision":0,"n_files":1,"n_statements":31,"n_excluded":0,"n_missing":1,"n_branches":0,"n_partial_branches":0,"n_missing_branches":0}}},"z_3baf1eb7e8e062db_formatting_py":{"hash":"fb1d55034f01eb0fc0d20c7b7486c2a0","index":{"url":"z_3baf1eb7e8e062db_formatting_py.html","file":"bustimes/formatting.py","description":"","nums":{"precision":0,"n_files":1,"n_statements":19,"n_excluded":0,"n_missing":0,"n_branches":0,"n_partial_branches":0,"n_missing_branches":0}}},"z_04b90725eef61805_bank_holidays_py":{"hash":"30a608e98cdd899e20b2e4ba523a746d","index":{"url":"z_04b90725eef61805_bank_holidays_py.html","file":"bustimes/management/commands/bank_holidays.py","description":"","nums":{"precision":0,"n_files":1,"n_statements":52,"n_excluded":0,"n_missing":1,"n_branches":0,"n_partial_branches":0,"n_missing_branches":0}}},"z_04b90725eef61805_import_atco_cif_py":{"hash":"38ea2fcb77279326f8deeb6534b938f0","index":{"url":"z_04b90725eef61805_import_atco_cif_py.html","file":"bustimes/management/commands/import_atco_cif.py","description":"","nums":{"precision":0,"n_files":1,"n_statements":235,"n_excluded":0,"n_missing":25,"n_branches":0,"n_partial_branches":0,"n_missing_branches":0}}},"z_04b90725eef61805_import_bod_timetables_py":{"hash":"27e3b3bcd6a9c459bb4afdcab6576af6","index":{"url":"z_04b90725eef61805_import_bod_timetables_py.html","file":"bustimes/management/commands/import_bod_timetables.py","description":"","nums":{"precision":0,"n_files":1,"n_statements":268,"n_excluded":0,"n_missing":24,"n_branches":0,"n_partial_branches":0,"n_missing_branches":0}}},"z_04b90725eef61805_import_gtfs_py":{"hash":"afd8ac72cd24f7cb7854403f361b6cc0","index":{"url":"z_04b90725eef61805_import_gtfs_py.html","file":"bustimes/management/commands/import_gtfs.py","description":"","nums":{"precision":0,"n_files":1,"n_statements":237,"n_excluded":0,"n_missing":23,"n_branches":0,"n_partial_branches":0,"n_missing_branches":0}}},"z_04b90725eef61805_import_gtfs_ember_py":{"hash":"135918d369a8effc02086cf0e9f6be3c","index":{"url":"z_04b90725eef61805_import_gtfs_ember_py.html","file":"bustimes/management/commands/import_gtfs_ember.py","description":"","nums":{"precision":0,"n_files":1,"n_statements":103,"n_excluded":0,"n_missing":6,"n_branches":0,"n_partial_branches":0,"n_missing_branches":0}}},"z_04b90725eef61805_import_gtfs_flixbus_py":{"hash":"f095bb5153d69776077e9720839da7ad","index":{"url":"z_04b90725eef61805_import_gtfs_flixbus_py.html","file":"bustimes/management/commands/import_gtfs_flixbus.py","description":"","nums":{"precision":0,"n_files":1,"n_statements":144,"n_excluded":0,"n_missing":3,"n_branches":0,"n_partial_branches":0,"n_missing_branches":0}}},"z_04b90725eef61805_import_ni_py":{"hash":"f515eba793053b3843854b510fdd61a2","index":{"url":"z_04b90725eef61805_import_ni_py.html","file":"bustimes/management/commands/import_ni.py","description":"","nums":{"precision":0,"n_files":1,"n_statements":31,"n_excluded":0,"n_missing":0,"n_branches":0,"n_partial_branches":0,"n_missing_branches":0}}},"z_04b90725eef61805_import_passenger_py":{"hash":"5d48b2efb1181a138f92fa8f1d0afa4b","index":{"url":"z_04b90725eef61805_import_passenger_py.html","file":"bustimes/management/commands/import_passenger.py","description":"","nums":{"precision":0,"n_files":1,"n_statements":116,"n_excluded":0,"n_missing":34,"n_branches":0,"n_partial_branches":0,"n_missing_branches":0}}},"z_04b90725eef61805_import_tnds_py":{"hash":"2397acf535c654739a4a1d2c6d0b19c7","index":{"url":"z_04b90725eef61805_import_tnds_py.html","file":"bustimes/management/commands/import_tnds.py","description":"","nums":{"precision":0,"n_files":1,"n_statements":43,"n_excluded":0,"n_missing":0,"n_branches":0,"n_partial_branches":0,"n_missing_branches":0}}},"z_04b90725eef61805_import_transxchange_py":{"hash":"8d62f6a080beafcb0d50f68515ca2821","index":{"url":"z_04b90725eef61805_import_transxchange_py.html","file":"bustimes/management/commands/import_transxchange.py","description":"","nums":{"precision":0,"n_files":1,"n_statements":772,"n_excluded":0,"n_missing":77,"n_branches":0,"n_partial_branches":0,"n_missing_branches":0}}},"z_06bcf2d2e74f1893_test_bank_holidays_py":{"hash":"3cb7db3692578fe61520c9ea490f94c6","index":{"url":"z_06bcf2d2e74f1893_test_bank_holidays_py.html","file":"bustimes/management/tests/test_bank_holidays.py","description":"","nums":{"precision":0,"n_files":1,"n_statements":20,"n_excluded":0,"n_missing":0,"n_branches":0,"n_partial_branches":0,"n_missing_branches":0}}},"z_06bcf2d2e74f1893_test_import_atco_cif_py":{"hash":"b1a4366f1e07cf05e7daf5cc8dbe5e15","index":{"url":"z_06bcf2d2e74f1893_test_import_atco_cif_py.html","file":"bustimes/management/tests/test_import_atco_cif.py","description":"","nums":{"precision":0,"n_files":1,"n_statements":70,"n_excluded":0,"n_missing":0,"n_branches":0,"n_partial_branches":0,"n_missing_branches":0}}},"z_06bcf2d2e74f1893_test_import_bod_py":{"hash":"4f734dc823cd82a36bd84172c2c25b7a","index":{"url":"z_06bcf2d2e74f1893_test_import_bod_py.html","file":"bustimes/management/tests/test_import_bod.py","description":"","nums":{"precision":0,"n_files":1,"n_statements":242,"n_excluded":0,"n_missing":0,"n_branches":0,"n_partial_branches":0,"n_missing_branches":0}}},"z_06bcf2d2e74f1893_test_import_gtfs_py":{"hash":"dfb2d279c5e03c5c01eb11aabc985bc7","index":{"url":"z_06bcf2d2e74f1893_test_import_gtfs_py.html","file":"bustimes/management/tests/test_import_gtfs.py","description":"","nums":{"precision":0,"n_files":1,"n_statements":103,"n_excluded":0,"n_missing":0,"n_branches":0,"n_partial_branches":0,"n_missing_branches":0}}},"z_06bcf2d2e74f1893_test_import_gtfs_ember_flixbus_py":{"hash":"4aedd1e0984b488b54e5ae3403ccff55","index":{"url":"z_06bcf2d2e74f1893_test_import_gtfs_ember_flixbus_py.html","file":"bustimes/management/tests/test_import_gtfs_ember_flixbus.py","description":"","nums":{"precision":0,"n_files":1,"n_statements":78,"n_excluded":0,"n_missing":0,"n_branches":0,"n_partial_branches":0,"n_missing_branches":0}}},"z_06bcf2d2e74f1893_test_import_ni_py":{"hash":"23f48330e13ec6c184808934a39a4b9c","index":{"url":"z_06bcf2d2e74f1893_test_import_ni_py.html","file":"bustimes/management/tests/test_import_ni.py","description":"","nums":{"precision":0,"n_files":1,"n_statements":21,"n_excluded":0,"n_missing":0,"n_branches":0,"n_partial_branches":0,"n_missing_branches":0}}},"z_06bcf2d2e74f1893_test_import_passenger_py":{"hash":"11e5fc0ace70b4663cf9ef1e15508411","index":{"url":"z_06bcf2d2e74f1893_test_import_passenger_py.html","file":"bustimes/management/tests/test_import_passenger.py","description":"","nums":{"precision":0,"n_files":1,"n_statements":23,"n_excluded":0,"n_missing":0,"n_branches":0,"n_partial_branches":0,"n_missing_branches":0}}},"z_06bcf2d2e74f1893_test_import_transxchange_py":{"hash":"3f8cd83b4d26084c3a2a3646f7cb21e3","index":{"url":"z_06bcf2d2e74f1893_test_import_transxchange_py.html","file":"bustimes/management/tests/test_import_transxchange.py","description":"","nums":{"precision":0,"n_files":1,"n_statements":742,"n_excluded":0,"n_missing":0,"n_branches":0,"n_partial_branches":0,"n_missing_branches":0}}},"z_06bcf2d2e74f1893_test_tnds_py":{"hash":"440cac9cbf29d9cb8d6ce3a13271189b","index":{"url":"z_06bcf2d2e74f1893_test_tnds_py.html","file":"bustimes/management/tests/test_tnds.py","description":"","nums":{"precision":0,"n_files":1,"n_statements":19,"n_excluded":0,"n_missing":0,"n_branches":0,"n_partial_branches":0,"n_missing_branches":0}}},"z_3baf1eb7e8e062db_models_py":{"hash":"7ff8a18097120851671bf891032d74a5","index":{"url":"z_3baf1eb7e8e062db_models_py.html","file":"bustimes/models.py","description":"","nums":{"precision":0,"n_files":1,"n_statements":335,"n_excluded":0,"n_missing":6,"n_branches":0,"n_partial_branches":0,"n_missing_branches":0}}},"z_3baf1eb7e8e062db_tests_py":{"hash":"71d8ea925453b6aba82e14a8a1a81309","index":{"url":"z_3baf1eb7e8e062db_tests_py.html","file":"bustimes/tests.py","description":"","nums":{"precision":0,"n_files":1,"n_statements":132,"n_excluded":0,"n_missing":0,"n_branches":0,"n_partial_branches":0,"n_missing_branches":0}}},"z_3baf1eb7e8e062db_timetables_py":{"hash":"46f61fd42facc9163f2bd82c936c5b68","index":{"url":"z_3baf1eb7e8e062db_timetables_py.html","file":"bustimes/timetables.py","description":"","nums":{"precision":0,"n_files":1,"n_statements":637,"n_excluded":0,"n_missing":53,"n_branches":0,"n_partial_branches":0,"n_missing_branches":0}}},"z_3baf1eb7e8e062db_urls_py":{"hash":"a451847d6f2affeeadfe43ac485c8764","index":{"url":"z_3baf1eb7e8e062db_urls_py.html","file":"bustimes/urls.py","description":"","nums":{"precision":0,"n_files":1,"n_statements":3,"n_excluded":0,"n_missing":0,"n_branches":0,"n_partial_branches":0,"n_missing_branches":0}}},"z_3baf1eb7e8e062db_utils_py":{"hash":"a1649090a9c74612fff19b1acdc41944","index":{"url":"z_3baf1eb7e8e062db_utils_py.html","file":"bustimes/utils.py","description":"","nums":{"precision":0,"n_files":1,"n_statements":183,"n_excluded":0,"n_missing":11,"n_branches":0,"n_partial_branches":0,"n_missing_branches":0}}},"z_3baf1eb7e8e062db_views_py":{"hash":"d2e7a9e5d2f61d5b826d7b71cac4153a","index":{"url":"z_3baf1eb7e8e062db_views_py.html","file":"bustimes/views.py","description":"","nums":{"precision":0,"n_files":1,"n_statements":372,"n_excluded":0,"n_missing":75,"n_branches":0,"n_partial_branches":0,"n_missing_branches":0}}},"z_f5dba1c56a64fa65_avl_py":{"hash":"151577eaadec7cf40c2154aedd2a75e7","index":{"url":"z_f5dba1c56a64fa65_avl_py.html","file":"departures/avl.py","description":"","nums":{"precision":0,"n_files":1,"n_statements":12,"n_excluded":0,"n_missing":1,"n_branches":0,"n_partial_branches":0,"n_missing_branches":0}}},"z_f5dba1c56a64fa65_gtfsr_py":{"hash":"1ee0ce146dc1f57a145bd7c6ce8936e0","index":{"url":"z_f5dba1c56a64fa65_gtfsr_py.html","file":"departures/gtfsr.py","description":"","nums":{"precision":0,"n_files":1,"n_statements":91,"n_excluded":0,"n_missing":2,"n_branches":0,"n_partial_branches":0,"n_missing_branches":0}}},"z_f5dba1c56a64fa65_live_py":{"hash":"dbaafff799bb275bc48d1ba0cb3773b4","index":{"url":"z_f5dba1c56a64fa65_live_py.html","file":"departures/live.py","description":"","nums":{"precision":0,"n_files":1,"n_statements":134,"n_excluded":0,"n_missing":14,"n_branches":0,"n_partial_branches":0,"n_missing_branches":0}}},"z_f5dba1c56a64fa65_sources_py":{"hash":"1192cd4eb7c4318d6e9d88e85d77ab5e","index":{"url":"z_f5dba1c56a64fa65_sources_py.html","file":"departures/sources.py","description":"","nums":{"precision":0,"n_files":1,"n_statements":216,"n_excluded":0,"n_missing":33,"n_branches":0,"n_partial_branches":0,"n_missing_branches":0}}},"z_f5dba1c56a64fa65_test_gtfsr_trip_updates_py":{"hash":"8775aaa0f92325836cebf1b66e65774b","index":{"url":"z_f5dba1c56a64fa65_test_gtfsr_trip_updates_py.html","file":"departures/test_gtfsr_trip_updates.py","description":"","nums":{"precision":0,"n_files":1,"n_statements":45,"n_excluded":0,"n_missing":0,"n_branches":0,"n_partial_branches":0,"n_missing_branches":0}}},"z_f5dba1c56a64fa65_test_gtfsr_vehicle_positions_py":{"hash":"d656d4212a73c6f92a896a34b55abba9","index":{"url":"z_f5dba1c56a64fa65_test_gtfsr_vehicle_positions_py.html","file":"departures/test_gtfsr_vehicle_positions.py","description":"","nums":{"precision":0,"n_files":1,"n_statements":33,"n_excluded":0,"n_missing":0,"n_branches":0,"n_partial_branches":0,"n_missing_branches":0}}},"z_f5dba1c56a64fa65_test_live_py":{"hash":"585926ef4dd0e02cd6d9757025329512","index":{"url":"z_f5dba1c56a64fa65_test_live_py.html","file":"departures/test_live.py","description":"","nums":{"precision":0,"n_files":1,"n_statements":111,"n_excluded":0,"n_missing":0,"n_branches":0,"n_partial_branches":0,"n_missing_branches":0}}},"z_5eab78ae04e860eb_admin_py":{"hash":"7d8816291f23180f7e8a9a491d9517da","index":{"url":"z_5eab78ae04e860eb_admin_py.html","file":"disruptions/admin.py","description":"","nums":{"precision":0,"n_files":1,"n_statements":26,"n_excluded":0,"n_missing":1,"n_branches":0,"n_partial_branches":0,"n_missing_branches":0}}},"z_5eab78ae04e860eb_models_py":{"hash":"4aecf1049c5bd393e7b3a1d4728cd44b","index":{"url":"z_5eab78ae04e860eb_models_py.html","file":"disruptions/models.py","description":"","nums":{"precision":0,"n_files":1,"n_statements":72,"n_excluded":0,"n_missing":5,"n_branches":0,"n_partial_branches":0,"n_missing_branches":0}}},"z_5eab78ae04e860eb_siri_sx_py":{"hash":"93e4341ae8415f6c4e089155843e9bed","index":{"url":"z_5eab78ae04e860eb_siri_sx_py.html","file":"disruptions/siri_sx.py","description":"","nums":{"precision":0,"n_files":1,"n_statements":122,"n_excluded":0,"n_missing":14,"n_branches":0,"n_partial_branches":0,"n_missing_branches":0}}},"z_5eab78ae04e860eb_test_siri_sx_py":{"hash":"3be197a3564118463d888aa4140dc2fa","index":{"url":"z_5eab78ae04e860eb_test_siri_sx_py.html","file":"disruptions/test_siri_sx.py","description":"","nums":{"precision":0,"n_files":1,"n_statements":48,"n_excluded":0,"n_missing":0,"n_branches":0,"n_partial_branches":0,"n_missing_branches":0}}},"z_5eab78ae04e860eb_test_tfl_disruptions_py":{"hash":"0e6ace2ba225821e0572f0493f3f436c","index":{"url":"z_5eab78ae04e860eb_test_tfl_disruptions_py.html","file":"disruptions/test_tfl_disruptions.py","description":"","nums":{"precision":0,"n_files":1,"n_statements":34,"n_excluded":0,"n_missing":0,"n_branches":0,"n_partial_branches":0,"n_missing_branches":0}}},"z_5eab78ae04e860eb_tests_py":{"hash":"0f99e8a8c686215f7ce4662920e64654","index":{"url":"z_5eab78ae04e860eb_tests_py.html","file":"disruptions/tests.py","description":"","nums":{"precision":0,"n_files":1,"n_statements":16,"n_excluded":0,"n_missing":0,"n_branches":0,"n_partial_branches":0,"n_missing_branches":0}}},"z_5eab78ae04e860eb_tfl_disruptions_py":{"hash":"8e60231dfcb5e2453520a1cbf3ffb0d2","index":{"url":"z_5eab78ae04e860eb_tfl_disruptions_py.html","file":"disruptions/tfl_disruptions.py","description":"","nums":{"precision":0,"n_files":1,"n_statements":91,"n_excluded":0,"n_missing":2,"n_branches":0,"n_partial_branches":0,"n_missing_branches":0}}},"z_5eab78ae04e860eb_urls_py":{"hash":"d1ba29ccde41a0b995ce7fbbfebff37c","index":{"url":"z_5eab78ae04e860eb_urls_py.html","file":"disruptions/urls.py","description":"","nums":{"precision":0,"n_files":1,"n_statements":3,"n_excluded":0,"n_missing":0,"n_branches":0,"n_partial_branches":0,"n_missing_branches":0}}},"z_5eab78ae04e860eb_views_py":{"hash":"17b7adf9f00ba742533bf4a9fc45d52a","index":{"url":"z_5eab78ae04e860eb_views_py.html","file":"disruptions/views.py","description":"","nums":{"precision":0,"n_files":1,"n_statements":9,"n_excluded":0,"n_missing":0,"n_branches":0,"n_partial_branches":0,"n_missing_branches":0}}},"z_1926e95c90261592_admin_py":{"hash":"d216a633e91b3969b1fa3eaa2388f3ae","index":{"url":"z_1926e95c90261592_admin_py.html","file":"fares/admin.py","description":"","nums":{"precision":0,"n_files":1,"n_statements":37,"n_excluded":0,"n_missing":2,"n_branches":0,"n_partial_branches":0,"n_missing_branches":0}}},"z_1926e95c90261592_forms_py":{"hash":"e2611bb5e9e0f07e9229136cf13ec34a","index":{"url":"z_1926e95c90261592_forms_py.html","file":"fares/forms.py","description":"","nums":{"precision":0,"n_files":1,"n_statements":26,"n_excluded":0,"n_missing":3,"n_branches":0,"n_partial_branches":0,"n_missing_branches":0}}},"z_1baea51d5a18881d_import_netex_fares_py":{"hash":"ebc183731362a6198571d80b21ea94f7","index":{"url":"z_1baea51d5a18881d_import_netex_fares_py.html","file":"fares/management/commands/import_netex_fares.py","description":"","nums":{"precision":0,"n_files":1,"n_statements":353,"n_excluded":0,"n_missing":59,"n_branches":0,"n_partial_branches":0,"n_missing_branches":0}}},"z_1baea51d5a18881d_mytrip_ticketing_py":{"hash":"b4d0794366e4f83f981cc00221a6d4d9","index":{"url":"z_1baea51d5a18881d_mytrip_ticketing_py.html","file":"fares/management/commands/mytrip_ticketing.py","description":"","nums":{"precision":0,"n_files":1,"n_statements":38,"n_excluded":0,"n_missing":3,"n_branches":0,"n_partial_branches":0,"n_missing_branches":0}}},"z_1926e95c90261592_models_py":{"hash":"2b00f1a67f1e1b1080ec2e046fc87285","index":{"url":"z_1926e95c90261592_models_py.html","file":"fares/models.py","description":"","nums":{"precision":0,"n_files":1,"n_statements":176,"n_excluded":0,"n_missing":8,"n_branches":0,"n_partial_branches":0,"n_missing_branches":0}}},"z_1926e95c90261592_mytrip_py":{"hash":"abc2b3bbec38dd9bf340f4048ae73fff","index":{"url":"z_1926e95c90261592_mytrip_py.html","file":"fares/mytrip.py","description":"","nums":{"precision":0,"n_files":1,"n_statements":53,"n_excluded":0,"n_missing":4,"n_branches":0,"n_partial_branches":0,"n_missing_branches":0}}},"z_1926e95c90261592_test_mytrip_py":{"hash":"d4725fa030c3bd55d11f73e5c8db2be9","index":{"url":"z_1926e95c90261592_test_mytrip_py.html","file":"fares/test_mytrip.py","description":"","nums":{"precision":0,"n_files":1,"n_statements":40,"n_excluded":0,"n_missing":0,"n_branches":0,"n_partial_branches":0,"n_missing_branches":0}}},"z_1926e95c90261592_tests_py":{"hash":"9c7dd0df482b2a0ddff000442363f348","index":{"url":"z_1926e95c90261592_tests_py.html","file":"fares/tests.py","description":"","nums":{"precision":0,"n_files":1,"n_statements":79,"n_excluded":0,"n_missing":0,"n_branches":0,"n_partial_branches":0,"n_missing_branches":0}}},"z_1926e95c90261592_urls_py":{"hash":"e765c14315ab54259211cc35c7af19ef","index":{"url":"z_1926e95c90261592_urls_py.html","file":"fares/urls.py","description":"","nums":{"precision":0,"n_files":1,"n_statements":3,"n_excluded":0,"n_missing":0,"n_branches":0,"n_partial_branches":0,"n_missing_branches":0}}},"z_1926e95c90261592_views_py":{"hash":"0a88782cf7e50b27274605cf939c70f6","index":{"url":"z_1926e95c90261592_views_py.html","file":"fares/views.py","description":"","nums":{"precision":0,"n_files":1,"n_statements":44,"n_excluded":0,"n_missing":0,"n_branches":0,"n_partial_branches":0,"n_missing_branches":0}}},"manage_py":{"hash":"050e30999a8656d98f7c79bd5a0e8b6a","index":{"url":"manage_py.html","file":"manage.py","description":"","nums":{"precision":0,"n_files":1,"n_statements":6,"n_excluded":0,"n_missing":0,"n_branches":0,"n_partial_branches":0,"n_missing_branches":0}}},"z_f06ab0b21e42ca84_test_txc_py":{"hash":"bdb4709e19eac802bedab044cba504fb","index":{"url":"z_f06ab0b21e42ca84_test_txc_py.html","file":"transxchange/test_txc.py","description":"","nums":{"precision":0,"n_files":1,"n_statements":23,"n_excluded":0,"n_missing":0,"n_branches":0,"n_partial_branches":0,"n_missing_branches":0}}},"z_f06ab0b21e42ca84_txc_py":{"hash":"f4dff93ebe36eb98e1667921965a7bae","index":{"url":"z_f06ab0b21e42ca84_txc_py.html","file":"transxchange/txc.py","description":"","nums":{"precision":0,"n_files":1,"n_statements":480,"n_excluded":0,"n_missing":18,"n_branches":0,"n_partial_branches":0,"n_missing_branches":0}}},"z_6a478a4b3744fc7a_admin_py":{"hash":"b04331b0aa3364f8111e062f6e33e708","index":{"url":"z_6a478a4b3744fc7a_admin_py.html","file":"vehicles/admin.py","description":"","nums":{"precision":0,"n_files":1,"n_statements":249,"n_excluded":0,"n_missing":34,"n_branches":0,"n_partial_branches":0,"n_missing_branches":0}}},"z_6a478a4b3744fc7a_apps_py":{"hash":"3292d72ac5aba4cf47e43c896e369fd5","index":{"url":"z_6a478a4b3744fc7a_apps_py.html","file":"vehicles/apps.py","description":"","nums":{"precision":0,"n_files":1,"n_statements":6,"n_excluded":0,"n_missing":0,"n_branches":0,"n_partial_branches":0,"n_missing_branches":0}}},"z_6a478a4b3744fc7a_context_processors_py":{"hash":"3431ee3d49e2c93aea4056904ce00cbc","index":{"url":"z_6a478a4b3744fc7a_context_processors_py.html","file":"vehicles/context_processors.py","description":"","nums":{"precision":0,"n_files":1,"n_statements":14,"n_excluded":0,"n_missing":0,"n_branches":0,"n_partial_branches":0,"n_missing_branches":0}}},"z_6a478a4b3744fc7a_fields_py":{"hash":"2a7c9f29c3d3b69f0ca4d2227e80fbbf","index":{"url":"z_6a478a4b3744fc7a_fields_py.html","file":"vehicles/fields.py","description":"","nums":{"precision":0,"n_files":1,"n_statements":23,"n_excluded":0,"n_missing":0,"n_branches":0,"n_partial_branches":0,"n_missing_branches":0}}},"z_6a478a4b3744fc7a_filters_py":{"hash":"2741b6da17fca3291a8d3e69e19410e2","index":{"url":"z_6a478a4b3744fc7a_filters_py.html","file":"vehicles/filters.py","description":"","nums":{"precision":0,"n_files":1,"n_statements":20,"n_excluded":0,"n_missing":0,"n_branches":0,"n_partial_branches":0,"n_missing_branches":0}}},"z_6a478a4b3744fc7a_form_fields_py":{"hash":"afeebe6efed12e3e2d04e663aec51ac8","index":{"url":"z_6a478a4b3744fc7a_form_fields_py.html","file":"vehicles/form_fields.py","description":"","nums":{"precision":0,"n_files":1,"n_statements":15,"n_excluded":0,"n_missing":0,"n_branches":0,"n_partial_branches":0,"n_missing_branches":0}}},"z_6a478a4b3744fc7a_forms_py":{"hash":"6a08b78e59e0eafd665f3bee19b1f89a","index":{"url":"z_6a478a4b3744fc7a_forms_py.html","file":"vehicles/forms.py","description":"","nums":{"precision":0,"n_files":1,"n_statements":94,"n_excluded":0,"n_missing":3,"n_branches":0,"n_partial_branches":0,"n_missing_branches":0}}},"z_75b41f4b22c00b34_import_bod_avl_py":{"hash":"e97d71b79389ef4cb62de45f38692e35","index":{"url":"z_75b41f4b22c00b34_import_bod_avl_py.html","file":"vehicles/management/commands/import_bod_avl.py","description":"","nums":{"precision":0,"n_files":1,"n_statements":456,"n_excluded":0,"n_missing":55,"n_branches":0,"n_partial_branches":0,"n_missing_branches":0}}},"z_75b41f4b22c00b34_import_bushub_py":{"hash":"f7432aa40797c04ccfe9ffb3721fc579","index":{"url":"z_75b41f4b22c00b34_import_bushub_py.html","file":"vehicles/management/commands/import_bushub.py","description":"","nums":{"precision":0,"n_files":1,"n_statements":72,"n_excluded":0,"n_missing":14,"n_branches":0,"n_partial_branches":0,"n_missing_branches":0}}},"z_75b41f4b22c00b34_import_edinburgh_py":{"hash":"64bc3a98d7e9c54c3496f57dac776a17","index":{"url":"z_75b41f4b22c00b34_import_edinburgh_py.html","file":"vehicles/management/commands/import_edinburgh.py","description":"","nums":{"precision":0,"n_files":1,"n_statements":72,"n_excluded":0,"n_missing":4,"n_branches":0,"n_partial_branches":0,"n_missing_branches":0}}},"z_75b41f4b22c00b34_import_gtfsr_ember_py":{"hash":"e1155f4bd76d146f3a244ca42674cf96","index":{"url":"z_75b41f4b22c00b34_import_gtfsr_ember_py.html","file":"vehicles/management/commands/import_gtfsr_ember.py","description":"","nums":{"precision":0,"n_files":1,"n_statements":87,"n_excluded":0,"n_missing":6,"n_branches":0,"n_partial_branches":0,"n_missing_branches":0}}},"z_75b41f4b22c00b34_import_gtfsr_ie_py":{"hash":"a3f6e9d202429b4ff4909e0e7f3cfa54","index":{"url":"z_75b41f4b22c00b34_import_gtfsr_ie_py.html","file":"vehicles/management/commands/import_gtfsr_ie.py","description":"","nums":{"precision":0,"n_files":1,"n_statements":104,"n_excluded":0,"n_missing":6,"n_branches":0,"n_partial_branches":0,"n_missing_branches":0}}},"z_75b41f4b22c00b34_import_live_jersey_py":{"hash":"74be7a9af8af215940a97932235cfdc6","index":{"url":"z_75b41f4b22c00b34_import_live_jersey_py.html","file":"vehicles/management/commands/import_live_jersey.py","description":"","nums":{"precision":0,"n_files":1,"n_statements":35,"n_excluded":0,"n_missing":0,"n_branches":0,"n_partial_branches":0,"n_missing_branches":0}}},"z_75b41f4b22c00b34_import_nx_py":{"hash":"d88ee16fd873c3b0152616963e52c0a5","index":{"url":"z_75b41f4b22c00b34_import_nx_py.html","file":"vehicles/management/commands/import_nx.py","description":"","nums":{"precision":0,"n_files":1,"n_statements":137,"n_excluded":0,"n_missing":27,"n_branches":0,"n_partial_branches":0,"n_missing_branches":0}}},"z_75b41f4b22c00b34_import_polar_py":{"hash":"8df65d6f8aab32adc673c99e254a8280","index":{"url":"z_75b41f4b22c00b34_import_polar_py.html","file":"vehicles/management/commands/import_polar.py","description":"","nums":{"precision":0,"n_files":1,"n_statements":75,"n_excluded":0,"n_missing":25,"n_branches":0,"n_partial_branches":0,"n_missing_branches":0}}},"z_75b41f4b22c00b34_import_stagecoach_avl_py":{"hash":"10db98e7aac93aa1820c222fd214150e","index":{"url":"z_75b41f4b22c00b34_import_stagecoach_avl_py.html","file":"vehicles/management/commands/import_stagecoach_avl.py","description":"","nums":{"precision":0,"n_files":1,"n_statements":94,"n_excluded":0,"n_missing":15,"n_branches":0,"n_partial_branches":0,"n_missing_branches":0}}},"z_75b41f4b22c00b34_signalr_py":{"hash":"4597e714a84a9f3d4e733cf5624b9dab","index":{"url":"z_75b41f4b22c00b34_signalr_py.html","file":"vehicles/management/commands/signalr.py","description":"","nums":{"precision":0,"n_files":1,"n_statements":66,"n_excluded":0,"n_missing":5,"n_branches":0,"n_partial_branches":0,"n_missing_branches":0}}},"z_75b41f4b22c00b34_siri_vm_subscribe_py":{"hash":"05f0d3408b305b719acb9aa6d3989697","index":{"url":"z_75b41f4b22c00b34_siri_vm_subscribe_py.html","file":"vehicles/management/commands/siri_vm_subscribe.py","description":"","nums":{"precision":0,"n_files":1,"n_statements":26,"n_excluded":0,"n_missing":7,"n_branches":0,"n_partial_branches":0,"n_missing_branches":0}}},"z_a67062fb53ecb6ec_import_live_vehicles_py":{"hash":"4dc6cb2de347678b1e97508665ea2e51","index":{"url":"z_a67062fb53ecb6ec_import_live_vehicles_py.html","file":"vehicles/management/import_live_vehicles.py","description":"","nums":{"precision":0,"n_files":1,"n_statements":283,"n_excluded":0,"n_missing":58,"n_branches":0,"n_partial_branches":0,"n_missing_branches":0}}},"z_47b23bc14ee40030_test_bod_avl_py":{"hash":"6a430aa8393a61400fc6691146962a02","index":{"url":"z_47b23bc14ee40030_test_bod_avl_py.html","file":"vehicles/management/tests/test_bod_avl.py","description":"","nums":{"precision":0,"n_files":1,"n_statements":295,"n_excluded":0,"n_missing":0,"n_branches":0,"n_partial_branches":0,"n_missing_branches":0}}},"z_47b23bc14ee40030_test_bushub_py":{"hash":"bea68905bd2085eb71ec98e6638e0b5d","index":{"url":"z_47b23bc14ee40030_test_bushub_py.html","file":"vehicles/management/tests/test_bushub.py","description":"","nums":{"precision":0,"n_files":1,"n_statements":48,"n_excluded":0,"n_missing":0,"n_branches":0,"n_partial_branches":0,"n_missing_branches":0}}},"z_47b23bc14ee40030_test_edinburgh_py":{"hash":"1ec7652a2b101a04428b3f68d45f93f8","index":{"url":"z_47b23bc14ee40030_test_edinburgh_py.html","file":"vehicles/management/tests/test_edinburgh.py","description":"","nums":{"precision":0,"n_files":1,"n_statements":51,"n_excluded":0,"n_missing":0,"n_branches":0,"n_partial_branches":0,"n_missing_branches":0}}},"z_47b23bc14ee40030_test_import_live_jersey_py":{"hash":"d1386fa72b1fc9485810f8252cada289","index":{"url":"z_47b23bc14ee40030_test_import_live_jersey_py.html","file":"vehicles/management/tests/test_import_live_jersey.py","description":"","nums":{"precision":0,"n_files":1,"n_statements":31,"n_excluded":0,"n_missing":0,"n_branches":0,"n_partial_branches":0,"n_missing_branches":0}}},"z_47b23bc14ee40030_test_import_nx_py":{"hash":"b23fc92a01279485e8011c685359fcea","index":{"url":"z_47b23bc14ee40030_test_import_nx_py.html","file":"vehicles/management/tests/test_import_nx.py","description":"","nums":{"precision":0,"n_files":1,"n_statements":43,"n_excluded":0,"n_missing":0,"n_branches":0,"n_partial_branches":0,"n_missing_branches":0}}},"z_47b23bc14ee40030_test_polar_py":{"hash":"97952a7274b112b885dbc6a85dd55e7a","index":{"url":"z_47b23bc14ee40030_test_polar_py.html","file":"vehicles/management/tests/test_polar.py","description":"","nums":{"precision":0,"n_files":1,"n_statements":33,"n_excluded":0,"n_missing":0,"n_branches":0,"n_partial_branches":0,"n_missing_branches":0}}},"z_47b23bc14ee40030_test_signalr_py":{"hash":"3021f61e5fd46746d46827497480403c","index":{"url":"z_47b23bc14ee40030_test_signalr_py.html","file":"vehicles/management/tests/test_signalr.py","description":"","nums":{"precision":0,"n_files":1,"n_statements":22,"n_excluded":0,"n_missing":0,"n_branches":0,"n_partial_branches":0,"n_missing_branches":0}}},"z_47b23bc14ee40030_test_siri_post_py":{"hash":"e5d72e44f4d3abfa4acb94c0e9a22f95","index":{"url":"z_47b23bc14ee40030_test_siri_post_py.html","file":"vehicles/management/tests/test_siri_post.py","description":"","nums":{"precision":0,"n_files":1,"n_statements":40,"n_excluded":0,"n_missing":0,"n_branches":0,"n_partial_branches":0,"n_missing_branches":0}}},"z_47b23bc14ee40030_test_stagecoach_avl_py":{"hash":"b7e64cd6781bbf5a4663b069b5b92936","index":{"url":"z_47b23bc14ee40030_test_stagecoach_avl_py.html","file":"vehicles/management/tests/test_stagecoach_avl.py","description":"","nums":{"precision":0,"n_files":1,"n_statements":33,"n_excluded":0,"n_missing":0,"n_branches":0,"n_partial_branches":0,"n_missing_branches":0}}},"z_47b23bc14ee40030_test_stats_py":{"hash":"96169a7a110638d84e4ebc7714dc2260","index":{"url":"z_47b23bc14ee40030_test_stats_py.html","file":"vehicles/management/tests/test_stats.py","description":"","nums":{"precision":0,"n_files":1,"n_statements":24,"n_excluded":0,"n_missing":0,"n_branches":0,"n_partial_branches":0,"n_missing_branches":0}}},"z_6a478a4b3744fc7a_models_py":{"hash":"d92e9480ce455d8d1cc530c3ad2896e2","index":{"url":"z_6a478a4b3744fc7a_models_py.html","file":"vehicles/models.py","description":"","nums":{"precision":0,"n_files":1,"n_statements":503,"n_excluded":0,"n_missing":37,"n_branches":0,"n_partial_branches":0,"n_missing_branches":0}}},"z_6a478a4b3744fc7a_rtpi_py":{"hash":"3208be09d3b5b717cc96d61c8bef3618","index":{"url":"z_6a478a4b3744fc7a_rtpi_py.html","file":"vehicles/rtpi.py","description":"","nums":{"precision":0,"n_files":1,"n_statements":76,"n_excluded":0,"n_missing":1,"n_branches":0,"n_partial_branches":0,"n_missing_branches":0}}},"z_6a478a4b3744fc7a_signals_py":{"hash":"51f5808031884f81dc6da2f1c4a22c4f","index":{"url":"z_6a478a4b3744fc7a_signals_py.html","file":"vehicles/signals.py","description":"","nums":{"precision":0,"n_files":1,"n_statements":11,"n_excluded":0,"n_missing":0,"n_branches":0,"n_partial_branches":0,"n_missing_branches":0}}},"z_6a478a4b3744fc7a_tasks_py":{"hash":"74d2ce61189172c99a2d6d768acddd7e","index":{"url":"z_6a478a4b3744fc7a_tasks_py.html","file":"vehicles/tasks.py","description":"","nums":{"precision":0,"n_files":1,"n_statements":132,"n_excluded":0,"n_missing":20,"n_branches":0,"n_partial_branches":0,"n_missing_branches":0}}},"z_6a478a4b3744fc7a_test_models_py":{"hash":"cf0659d7fe0df7141710705ff7ce084c","index":{"url":"z_6a478a4b3744fc7a_test_models_py.html","file":"vehicles/test_models.py","description":"","nums":{"precision":0,"n_files":1,"n_statements":62,"n_excluded":0,"n_missing":0,"n_branches":0,"n_partial_branches":0,"n_missing_branches":0}}},"z_6a478a4b3744fc7a_test_schedule_adherence_py":{"hash":"a57e59ff3537502aa7d18bc9d5e2a954","index":{"url":"z_6a478a4b3744fc7a_test_schedule_adherence_py.html","file":"vehicles/test_schedule_adherence.py","description":"","nums":{"precision":0,"n_files":1,"n_statements":75,"n_excluded":0,"n_missing":0,"n_branches":0,"n_partial_branches":0,"n_missing_branches":0}}},"z_6a478a4b3744fc7a_tests_py":{"hash":"299d2cb9016561b91f60cde048e18d04","index":{"url":"z_6a478a4b3744fc7a_tests_py.html","file":"vehicles/tests.py","description":"","nums":{"precision":0,"n_files":1,"n_statements":439,"n_excluded":0,"n_missing":0,"n_branches":0,"n_partial_branches":0,"n_missing_branches":0}}},"z_6a478a4b3744fc7a_time_aware_polyline_py":{"hash":"740721659ccefe21efb758e8f26019c2","index":{"url":"z_6a478a4b3744fc7a_time_aware_polyline_py.html","file":"vehicles/time_aware_polyline.py","description":"","nums":{"precision":0,"n_files":1,"n_statements":56,"n_excluded":0,"n_missing":28,"n_branches":0,"n_partial_branches":0,"n_missing_branches":0}}},"z_6a478a4b3744fc7a_urls_py":{"hash":"2ac79242f07c08a6c8584182235f180b","index":{"url":"z_6a478a4b3744fc7a_urls_py.html","file":"vehicles/urls.py","description":"","nums":{"precision":0,"n_files":1,"n_statements":4,"n_excluded":0,"n_missing":0,"n_branches":0,"n_partial_branches":0,"n_missing_branches":0}}},"z_6a478a4b3744fc7a_utils_py":{"hash":"945e124682badf82816b3ce49e469a34","index":{"url":"z_6a478a4b3744fc7a_utils_py.html","file":"vehicles/utils.py","description":"","nums":{"precision":0,"n_files":1,"n_statements":128,"n_excluded":0,"n_missing":6,"n_branches":0,"n_partial_branches":0,"n_missing_branches":0}}},"z_6a478a4b3744fc7a_views_py":{"hash":"a4016d0407bd7d490e912b2513a8062c","index":{"url":"z_6a478a4b3744fc7a_views_py.html","file":"vehicles/views.py","description":"","nums":{"precision":0,"n_files":1,"n_statements":594,"n_excluded":0,"n_missing":61,"n_branches":0,"n_partial_branches":0,"n_missing_branches":0}}},"z_2c17191315bcbf2a_admin_py":{"hash":"083e3b2f88eee95efdce6c2daaee290d","index":{"url":"z_2c17191315bcbf2a_admin_py.html","file":"vosa/admin.py","description":"","nums":{"precision":0,"n_files":1,"n_statements":36,"n_excluded":0,"n_missing":0,"n_branches":0,"n_partial_branches":0,"n_missing_branches":0}}},"z_081b736c8ed89381_import_vosa_py":{"hash":"6922b3ba244675beb63c18ae73467332","index":{"url":"z_081b736c8ed89381_import_vosa_py.html","file":"vosa/management/commands/import_vosa.py","description":"","nums":{"precision":0,"n_files":1,"n_statements":162,"n_excluded":0,"n_missing":3,"n_branches":0,"n_partial_branches":0,"n_missing_branches":0}}},"z_2c17191315bcbf2a_models_py":{"hash":"afb982240b9e3c4aafca2750d21c3587","index":{"url":"z_2c17191315bcbf2a_models_py.html","file":"vosa/models.py","description":"","nums":{"precision":0,"n_files":1,"n_statements":75,"n_excluded":0,"n_missing":0,"n_branches":0,"n_partial_branches":0,"n_missing_branches":0}}},"z_2c17191315bcbf2a_tests_py":{"hash":"999172be60475a4df0f13ba99f69849d","index":{"url":"z_2c17191315bcbf2a_tests_py.html","file":"vosa/tests.py","description":"","nums":{"precision":0,"n_files":1,"n_statements":60,"n_excluded":0,"n_missing":0,"n_branches":0,"n_partial_branches":0,"n_missing_branches":0}}},"z_2c17191315bcbf2a_urls_py":{"hash":"e57039ce03cf1e16fdcc9fc24db858aa","index":{"url":"z_2c17191315bcbf2a_urls_py.html","file":"vosa/urls.py","description":"","nums":{"precision":0,"n_files":1,"n_statements":3,"n_excluded":0,"n_missing":0,"n_branches":0,"n_partial_branches":0,"n_missing_branches":0}}},"z_2c17191315bcbf2a_views_py":{"hash":"eab3d1e5d8e72be564aae88861256e59","index":{"url":"z_2c17191315bcbf2a_views_py.html","file":"vosa/views.py","description":"","nums":{"precision":0,"n_files":1,"n_statements":57,"n_excluded":0,"n_missing":0,"n_branches":0,"n_partial_branches":0,"n_missing_branches":0}}}}}